rishi_raj/DELETE.py
rishi_raj/DISPLAY.py
rishi_raj/MAIN.py
rishi_raj/NEW_USER.py
rishi_raj/REG.py
rishi_raj/SEARCH.py
rishi_raj/UPDATE.py
student_rishiraj-1.0.1.dist-info/LICENSE
student_rishiraj-1.0.1.dist-info/METADATA
student_rishiraj-1.0.1.dist-info/WHEEL
student_rishiraj-1.0.1.dist-info/top_level.txt
student_rishiraj-1.0.1.dist-info/RECORD
